shifiq/__init__.py
shifiq/shifiq.py
shifiq/api/__init__.py
shifiq/api/connection.py
shifiq/api/player/__init__.py
shifiq/api/player/player.py
shifiq/client/__init__.py
shifiq/client/client.py
shifiq_sdk-0.0.5.dist-info/LICENSE
shifiq_sdk-0.0.5.dist-info/METADATA
shifiq_sdk-0.0.5.dist-info/WHEEL
shifiq_sdk-0.0.5.dist-info/top_level.txt
shifiq_sdk-0.0.5.dist-info/RECORD
