Metadata-Version: 2.1
Name: shifiq-sdk
Version: 0.0.5
Summary: Python SDK for ShifIQ
Author-email: Björn Benouarets <bjoern@secnex.io>
License: MIT License
Project-URL: Homepage, https://github.com/secnex/shifiq-sdk-python
Project-URL: Bug Tracker, https://github.com/secnex/shifiq-sdk-python/issues
Classifier: Programming Language :: Python :: 3
Classifier: License :: OSI Approved :: MIT License
Classifier: Operating System :: OS Independent
Requires-Python: >=3.7
License-File: LICENSE
Requires-Dist: requests >=2.25.0
Requires-Dist: websockets >=11.0.3
